mail_framework/__init__.py
mail_framework/sendmail.py
sanjumailgenerator-0.0.1.dist-info/LICENSE.txt
sanjumailgenerator-0.0.1.dist-info/METADATA
sanjumailgenerator-0.0.1.dist-info/WHEEL
sanjumailgenerator-0.0.1.dist-info/top_level.txt
sanjumailgenerator-0.0.1.dist-info/RECORD
